crossmodal/__init__.py
crossmodal-0.1.0.dist-info/METADATA
crossmodal-0.1.0.dist-info/WHEEL
crossmodal-0.1.0.dist-info/top_level.txt
crossmodal-0.1.0.dist-info/RECORD
